{
	"id": "b05fe25b-6ad1-4922-90c0-2dbd37338938",
	"name": "TwoMеnAndWomanWEareSocialNetworkEnvironment",
	"values": [
		{
			"key": "baseUrl",
			"value": "https://fast-plains-73661-971f43405213.herokuapp.com",
			"enabled": true
		},
		{
			"key": "baseURLWithAPI",
			"value": "{{baseUrl}}/api",
			"type": "default",
			"enabled": true
		},
		{
			"key": "createPostEndpoint",
			"value": "/api/post/auth/creator",
			"type": "default",
			"enabled": true
		},
		{
			"key": "editPostEndpoint",
			"value": "/api/post/auth/editor",
			"enabled": true
		},
		{
			"key": "authenticateEndpoint",
			"value": "/authenticate",
			"type": "default",
			"enabled": true
		},
		{
			"key": "latestPostEndpoint",
			"value": "/post/",
			"enabled": true
		},
		{
			"key": "deletePostEndpoint",
			"value": "/api/post/auth/manager",
			"enabled": true
		},
		{
			"key": "likesUpEndpoint",
			"value": "/api/post/auth/likesUp",
			"enabled": true
		},
		{
			"key": "editProfileEndpoint",
			"value": "/api/users/auth/",
			"type": "default",
			"enabled": true
		},
		{
			"key": "personalEndpoint",
			"value": "/personal",
			"type": "default",
			"enabled": true
		},
		{
			"key": "getUserRequestEndpoint",
			"value": "/api/auth/users/",
			"type": "default",
			"enabled": true
		},
		{
			"key": "requestEndpoint",
			"value": "/request/",
			"type": "default",
			"enabled": true
		},
		{
			"key": "approveEndpoint",
			"value": "approve",
			"type": "default",
			"enabled": true
		},
		{
			"key": "sendUserRequestEndpoint",
			"value": "/api/auth/request",
			"type": "default",
			"enabled": true
		},
		{
			"key": "usersURL",
			"value": "{{baseURLWithAPI}}/users",
			"type": "default",
			"enabled": true
		},
		{
			"key": "MrBeastUsername",
			"value": "MrBeast",
			"type": "default",
			"enabled": true
		},
		{
			"key": "MrBeastPassword",
			"value": "Abv123!",
			"type": "default",
			"enabled": true
		},
		{
			"key": "GeorgeBushUsername",
			"value": "GeorgeBush",
			"type": "default",
			"enabled": true
		},
		{
			"key": "GeorgeBushFirstName",
			"value": "George",
			"type": "default",
			"enabled": true
		},
		{
			"key": "GeorgeBushId",
			"value": "41",
			"type": "default",
			"enabled": true
		},
		{
			"key": "GeorgeBushPassword",
			"value": "Abv123*",
			"type": "default",
			"enabled": true
		},
		{
			"key": "MrBeastName",
			"value": "Mr Beast",
			"type": "default",
			"enabled": true
		},
		{
			"key": "MrBeastFirstName",
			"value": "Mr",
			"type": "default",
			"enabled": true
		},
		{
			"key": "MrBeastLastName",
			"value": " Beast",
			"type": "default",
			"enabled": true
		},
		{
			"key": "postByGeorgeBush",
			"value": "Initial Post by GeorgeBush using Postman",
			"type": "default",
			"enabled": true
		},
		{
			"key": "invalidPostByGeorgeBush",
			"value": "Lorem ipsum dolor sit amet, consectetuer adipiscing elit. Aenean commodo ligula eget dolor. Aenean massa. Cum sociis natoque penatibus et magnis dis parturient montes, nascetur ridiculus mus. Donec quam felis, ultricies nec, pellentesque eu, pretium quis, sem. Nulla consequat massa quis enim. Donec pede justo, fringilla vel, aliquet nec, vulputate eget, arcu. In enim justo, rhoncus ut, imperdiet a, venenatis vitae, justo. Nullam dictum felis eu pede mollis pretium. Integer tincidunt. Cras dapibus. Vivamus elementum semper nisi. Aenean vulputate eleifend tellus. Aenean leo ligula, porttitor eu, consequat vitae, eleifend ac, enim. Aliquam lorem ante, dapibus in, viverra quis, feugiat a, tellus. Phasellus viverra nulla ut metus varius laoreet. Quisque rutrum. Aenean imperdiet. Etiam ultricies nisi vel augue. Curabitur ullamcorper ultricies nisi. Nam eget dui. Etiam rhoncus. Maecenas tempus, tellus eget condimentum rhoncus, sem quam semper libero, sit amet adipiscing sem neque sed ipsum. Na",
			"type": "default",
			"enabled": true
		},
		{
			"key": "editPostByGeorgeBush",
			"value": "Edited Post by GeorgeBush using Postman",
			"type": "default",
			"enabled": true
		},
		{
			"key": "invalidPostByMrBeast",
			"value": "Lorem ipsum dolor sit amet, consectetuer adipiscing elit. Aenean commodo ligula eget dolor. Aenean massa. Cum sociis natoque penatibus et magnis dis parturient montes, nascetur ridiculus mus. Donec quam felis, ultricies nec, pellentesque eu, pretium quis, sem. Nulla consequat massa quis enim. Donec pede justo, fringilla vel, aliquet nec, vulputate eget, arcu. In enim justo, rhoncus ut, imperdiet a, venenatis vitae, justo. Nullam dictum felis eu pede mollis pretium. Integer tincidunt. Cras dapibus. Vivamus elementum semper nisi. Aenean vulputate eleifend tellus. Aenean leo ligula, porttitor eu, consequat vitae, eleifend ac, enim. Aliquam lorem ante, dapibus in, viverra quis, feugiat a, tellus. Phasellus viverra nulla ut metus varius laoreet. Quisque rutrum. Aenean imperdiet. Etiam ultricies nisi vel augue. Curabitur ullamcorper ultricies nisi. Nam eget dui. Etiam rhoncus. Maecenas tempus, tellus eget condimentum rhoncus, sem quam semper libero, sit amet adipiscing sem neque sed ipsum. Na",
			"type": "default",
			"enabled": true
		},
		{
			"key": "postByMrBeast",
			"value": "Initial Post by MrBeast using Postman",
			"type": "default",
			"enabled": true
		},
		{
			"key": "editPostByMrBeast",
			"value": "Edited Post by MrBeast using Postman",
			"type": "default",
			"enabled": true
		},
		{
			"key": "validJobTitle",
			"value": "Author",
			"type": "default",
			"enabled": true
		},
		{
			"key": "invalidName",
			"value": "Dani Sham",
			"type": "default",
			"enabled": true
		},
		{
			"key": "invalidJobTitle",
			"value": "Influencer",
			"type": "default",
			"enabled": true
		},
		{
			"key": "notFoundMessage",
			"value": "USER not found",
			"type": "default",
			"enabled": true
		},
		{
			"key": "randomUsername",
			"value": "",
			"type": "default",
			"enabled": true
		},
		{
			"key": "randomEmail",
			"value": "",
			"type": "default",
			"enabled": true
		},
		{
			"key": "registeredUserId",
			"value": "",
			"type": "any",
			"enabled": true
		},
		{
			"key": "MrBeastId",
			"value": "40",
			"type": "any",
			"enabled": true
		},
		{
			"key": "randomPassword",
			"value": "",
			"type": "default",
			"enabled": true
		},
		{
			"key": "invalidCyrillicUsername",
			"value": "Гошко",
			"type": "default",
			"enabled": true
		},
		{
			"key": "invalidEmailWithSpace",
			"value": "invalid email@weare.com",
			"type": "default",
			"enabled": true
		},
		{
			"key": "invalidUserName",
			"value": "PetTest",
			"type": "default",
			"enabled": true
		},
		{
			"key": "invalidId",
			"value": "500",
			"type": "default",
			"enabled": true
		},
		{
			"key": "adminUsername",
			"value": "adminYordan",
			"type": "default",
			"enabled": true
		},
		{
			"key": "adminPassword",
			"value": "Abv123!",
			"enabled": true
		},
		{
			"key": "adminName",
			"value": "Admin Boss",
			"type": "default",
			"enabled": true
		},
		{
			"key": "JackNicholsonUsername",
			"value": "JackNicholson",
			"type": "default",
			"enabled": true
		},
		{
			"key": "JackNicholsonPassword",
			"value": "TheJack123",
			"type": "default",
			"enabled": true
		},
		{
			"key": "JackNicholsonId",
			"value": "42",
			"type": "default",
			"enabled": true
		},
		{
			"key": "postByJackNicholson",
			"value": "You can't handle the truth!",
			"type": "default",
			"enabled": true
		},
		{
			"key": "TomCruiseUsername",
			"value": "TomCruise",
			"type": "default",
			"enabled": true
		},
		{
			"key": "TomCruisePassword",
			"value": "HaHaHa123!",
			"type": "default",
			"enabled": true
		},
		{
			"key": "createCommentEndpoint",
			"value": "/api/comment/auth/creator",
			"type": "default",
			"enabled": true
		},
		{
			"key": "commentByTomCruise",
			"value": "I want the truth!",
			"type": "default",
			"enabled": true
		},
		{
			"key": "editCommentContent",
			"value": "*Tom Cruise has left the courtroom",
			"type": "default",
			"enabled": true
		},
		{
			"key": "BahaMenUsername",
			"value": "BahaMen",
			"type": "default",
			"enabled": true
		},
		{
			"key": "BahaMenPassword",
			"value": "BauBau123!",
			"type": "default",
			"enabled": true
		},
		{
			"key": "postByBahaMen",
			"value": "Who let the dogs out?!",
			"type": "default",
			"enabled": true
		},
		{
			"key": "TheDogsUsername",
			"value": "TheDogs",
			"type": "default",
			"enabled": true
		},
		{
			"key": "TheDogsPassword",
			"value": "WofWof123!",
			"type": "default",
			"enabled": true
		},
		{
			"key": "commentByTheDogs",
			"value": "Woof, woof, woof, woof woof!",
			"type": "default",
			"enabled": true
		},
		{
			"key": "invalidCommentByTheDogs",
			"value": "",
			"type": "default",
			"enabled": true
		},
		{
			"key": "commentEditEndpoint",
			"value": "/api/comment/auth/editor",
			"type": "default",
			"enabled": true
		},
		{
			"key": "commentDeleteEndpoint",
			"value": "/api/comment/auth/manager",
			"type": "default",
			"enabled": true
		},
		{
			"key": "commentDeleteCheckEndpoint",
			"value": "/api/comment/single",
			"type": "default",
			"enabled": true
		},
		{
			"key": "commentLikeEndpoint",
			"value": "/api/comment/auth/likesUp",
			"type": "default",
			"enabled": true
		},
		{
			"key": "invalidPassword",
			"value": "123",
			"type": "default",
			"enabled": true
		},
		{
			"key": "WendyWendUsername",
			"value": "WendyWend",
			"type": "default",
			"enabled": true
		},
		{
			"key": "WendyWendPassword",
			"value": "iAmScared123!",
			"type": "default",
			"enabled": true
		},
		{
			"key": "usernameEditUser",
			"value": "telerikdani",
			"type": "default",
			"enabled": true
		},
		{
			"key": "passwordEditUser",
			"value": "123456",
			"type": "default",
			"enabled": true
		},
		{
			"key": "idEditUser",
			"value": "39",
			"type": "default",
			"enabled": true
		},
		{
			"key": "adminEditCommentContent",
			"value": "Admin edit comment",
			"type": "default",
			"enabled": true
		},
		{
			"key": "adminEditPostContent",
			"value": "Admin edit post",
			"type": "default",
			"enabled": true
		}
	],
	"_postman_variable_scope": "environment",
	"_postman_exported_at": "2023-10-15T09:27:41.410Z",
	"_postman_exported_using": "Postman/10.19.2"
}